yarl39
